{
  "total_questoes": 320,
  "total_los": 64,
  "questoes_por_lo": {
    "FL-1.1.1": 5,
    "FL-1.1.2": 5,
    "FL-1.2.1": 5,
    "FL-1.2.2": 5,
    "FL-1.2.3": 5,
    "FL-1.3.1": 5,
    "FL-1.4.1": 5,
    "FL-1.4.2": 5,
    "FL-1.4.3": 5,
    "FL-1.4.4": 5,
    "FL-1.4.5": 5,
    "FL-1.5.1": 5,
    "FL-1.5.2": 5,
    "FL-1.5.3": 5,
    "FL-2.1.1": 5,
    "FL-2.1.2": 5,
    "FL-2.1.3": 5,
    "FL-2.1.4": 5,
    "FL-2.1.5": 5,
    "FL-2.1.6": 5,
    "FL-2.2.1": 5,
    "FL-2.2.2": 5,
    "FL-2.2.3": 5,
    "FL-2.3.1": 5,
    "FL-3.1.1": 5,
    "FL-3.1.2": 5,
    "FL-3.1.3": 5,
    "FL-3.2.1": 5,
    "FL-3.2.2": 5,
    "FL-3.2.3": 5,
    "FL-3.2.4": 5,
    "FL-3.2.5": 5,
    "FL-4.1.1": 5,
    "FL-4.2.1": 5,
    "FL-4.2.2": 5,
    "FL-4.2.3": 5,
    "FL-4.2.4": 5,
    "FL-4.3.1": 5,
    "FL-4.3.2": 5,
    "FL-4.3.3": 5,
    "FL-4.4.1": 5,
    "FL-4.4.2": 5,
    "FL-4.4.3": 5,
    "FL-4.5.1": 5,
    "FL-4.5.2": 5,
    "FL-4.5.3": 5,
    "FL-5.1.1": 5,
    "FL-5.1.2": 5,
    "FL-5.1.3": 5,
    "FL-5.1.4": 5,
    "FL-5.1.5": 5,
    "FL-5.1.6": 5,
    "FL-5.1.7": 5,
    "FL-5.2.1": 5,
    "FL-5.2.2": 5,
    "FL-5.2.3": 5,
    "FL-5.2.4": 5,
    "FL-5.3.1": 5,
    "FL-5.3.2": 5,
    "FL-5.3.3": 5,
    "FL-5.4.1": 5,
    "FL-5.5.1": 5,
    "FL-6.1.1": 5,
    "FL-6.2.1": 5
  },
  "questoes_por_capitulo": {
    "1": 70,
    "2": 50,
    "3": 40,
    "4": 70,
    "5": 80,
    "6": 10
  },
  "distribuicao_simulado": {
    "1": 8,
    "2": 6,
    "3": 4,
    "4": 11,
    "5": 9,
    "6": 2
  },
  "itens_defasados_removidos_ou_rebaixados": [
    "ênfase em teste baseado em caso de uso como tópico central",
    "uso de “cobertura de sentença” como termo principal; substituído por teste de instrução",
    "uso de “cobertura de decisão” como termo principal; substituído por teste de ramificação",
    "seleção de ferramenta como eixo principal; reduzido para suporte de ferramentas e benefícios/riscos da automação",
    "BDD isolado; tratado apenas como exemplo de abordagem test-first/critério de aceite quando pertinente"
  ]
}